validate_adhar/__init__.py
validate_adhar/setup.py
validate_adhar/validate_adhar.py
validate_adhar-1.0.1.dist-info/METADATA
validate_adhar-1.0.1.dist-info/WHEEL
validate_adhar-1.0.1.dist-info/top_level.txt
validate_adhar-1.0.1.dist-info/RECORD
