Metadata-Version: 2.1
Name: validate-adhar
Version: 1.0.1
Summary: This Package is a Function to validate Adhaar Car and name
Home-page: UNKNOWN
Author: Oswald Fernandes
Author-email: oswfernand@yahoo.com
License: UNKNOWN
Platform: UNKNOWN
